{
  "input": {
    "id": "IusYMzmay3sU2VqCikC2Zs93WKoLzjCBbPoCdH35blw=",
    "private_key": "JsAS9fTd0ieiKWgYp+uOywGMJUMPaDuwfHHlSwOOYfEi6xgzOZrLexTZWoKKQLZmz3dYqgvOMIFs+gJ0ffluXA==",
    "peer_addrs": {
      "IusYMzmay3sU2VqCikC2Zs93WKoLzjCBbPoCdH35blw=": "47.89.188.82:8123",
      "cTwP5Vp8e2w1SUBRIHV5aNpQIZ+EBZyJ0obslzhLCuY=": "47.74.86.251:8124",
      "tpXRSKHHhGUtaQajCTsl82Wbaye+rAU3FFz9JXMm1YM=": "47.89.188.82:8125",
      "waQPY/v22gk0QDOvQb4VwMVnPNoig06KK8SiaaFA0+M=": "47.74.86.251:8126"
    },
    "node_settings": {
      "transaction_size": 128,
      "batch_size": 500,
      "mempool_size": 5000,
      "pretend_failure": false,
      "leader_rotation": 1000000,
      "gc_depth": 2000,
      "timeout": 5000
    },
    "consensus": {
      "Jasmine": {
        "minimal_batch_size_ratio": 0.8
      }
    },
    "test_mode": {
      "delay_test": false,
      "memory_test": false,
      "fault_tolerance_test": false
    },
    "logs": {},
    "metrics": {
      "enabled": true,
      "stop_after": null,
      "trace_finalization": false,
      "sampling_interval": 250,
      "export_path": "result-jasmine-n4-h2-f0-ts128-bs500-ir6000-lr1000000.json",
      "sampling_window": 40,
      "stop_after_stable": true,
      "stable_threshold": 1.0,
      "report_every_n_samples": 8,
      "stop_after_n_samples": 600
    },
    "client": {
      "use_instant_generator": false,
      "injection_rate": 6000
    }
  },
  "output": {
    "e2e_delay": 1132.1627044790653,
    "average_delay": 1075.3336927945472,
    "finalized_transactions": 410800,
    "consensus_throughput": 5.895268573396668,
    "key_block_ratio": 0.1912280701754386,
    "finalized_blocks": 1140,
    "key_block_delay": 942.6215633693391,
    "average_batch_size": 360.35087719298247,
    "block_delay": 61.12543859649123
  }
}