{
  "input": {
    "id": "EK3qMlN4XHdxas4V0ikDC3gxdZaJruIYvyUNl7HAWNY=",
    "private_key": "hKEWvM1gtciBuJb0m5Rm8+5dQ3NcndxneZqeKlCl/EAQreoyU3hcd3FqzhXSKQMLeDF1lomu4hi/JQ2XscBY1g==",
    "peer_addrs": {
      "EK3qMlN4XHdxas4V0ikDC3gxdZaJruIYvyUNl7HAWNY=": "47.89.188.82:8123",
      "QBLRmafylCrAmQvWS05qIuDVh7jmnCYR4KfjiN+K8BU=": "47.74.86.251:8124",
      "dEXVQI360k6jPzXIpyksNT3oISLlLQYnwDfQMFex3D0=": "47.89.188.82:8125",
      "2LcptvOol0uva3IIjuoVRqk1XdMwOo5KSC6WFvyU0rI=": "47.74.86.251:8126"
    },
    "node_settings": {
      "transaction_size": 128,
      "batch_size": 500,
      "mempool_size": 5000,
      "pretend_failure": false,
      "leader_rotation": 20,
      "gc_depth": 2000,
      "timeout": 5000
    },
    "consensus": {
      "Jasmine": {
        "minimal_batch_size_ratio": 0.8
      }
    },
    "test_mode": {
      "delay_test": false,
      "memory_test": false,
      "fault_tolerance_test": false
    },
    "logs": {},
    "metrics": {
      "enabled": true,
      "stop_after": null,
      "trace_finalization": false,
      "sampling_interval": 250,
      "export_path": "result-jasmine-n4-h2-f0-ts128-bs500-ir100-lr20.json",
      "sampling_window": 40,
      "stop_after_stable": true,
      "stable_threshold": 1.0,
      "report_every_n_samples": 8,
      "stop_after_n_samples": 600
    },
    "client": {
      "use_instant_generator": false,
      "injection_rate": 100
    }
  },
  "output": {
    "e2e_delay": 9893.424740683826,
    "average_delay": 1112.27721859393,
    "finalized_transactions": 65075,
    "consensus_throughput": 0.3844676828547796,
    "key_block_ratio": 0.9033333333333333,
    "finalized_blocks": 600,
    "key_block_delay": 1048.0362429104994,
    "average_batch_size": 108.45833333333333,
    "block_delay": 282.1
  }
}