{
  "input": {
    "id": "YmKoLHJOz7vadXga9fe18KbGO52kvjsr+jIpUAFDMeA=",
    "private_key": "QqlHhTqD9XEz1zeZZsHLzkkATQnIa8DQ8g/iuG0kTp1iYqgsck7Pu9p1eBr197XwpsY7naS+Oyv6MilQAUMx4A==",
    "peer_addrs": {
      "YmKoLHJOz7vadXga9fe18KbGO52kvjsr+jIpUAFDMeA=": "47.89.188.82:8123",
      "c1o6AmhE3Psv3u6CFxNDHNGqhQY04deWKwTWsb5fkl0=": "47.89.188.82:8124",
      "n9pjOsclWGmejv728AVeTrlfuVi/QIWOjJ2oOunLp/4=": "47.89.188.82:8125",
      "3o1/PZHw/wUI4MukPxyJ89yMvcEHoZFBVEsdBw4aQGU=": "47.89.188.82:8126"
    },
    "node_settings": {
      "transaction_size": 128,
      "batch_size": 250,
      "mempool_size": 5000,
      "pretend_failure": false,
      "leader_rotation": 5,
      "gc_depth": 4000,
      "timeout": 1500
    },
    "consensus": "HotStuff",
    "test_mode": {
      "delay_test": false,
      "memory_test": false,
      "fault_tolerance_test": false
    },
    "logs": {},
    "metrics": {
      "enabled": true,
      "stop_after": null,
      "trace_finalization": false,
      "sampling_interval": 250,
      "export_path": "result-hotstuff-n4-h1-f0-ts128-bs250-ir100-lr5.json",
      "sampling_window": 40,
      "stop_after_stable": true,
      "stable_threshold": 1,
      "report_every_n_samples": 8,
      "stop_after_n_samples": 300
    },
    "client": {
      "use_instant_generator": false,
      "injection_rate": 100
    },
    "delay": 0
  },
  "output": {
    "e2e_delay": 4.46,
    "average_delay": 1.49125,
    "finalized_transactions": 4000,
    "consensus_throughput": 0.4,
    "key_block_ratio": 1,
    "finalized_blocks": 22869,
    "key_block_delay": 1.49125,
    "average_batch_size": 0.17490926581835672,
    "block_delay": 0.4372731645458918
  }
}
